<fetchcollection>
  <fetch version="1.0">
    <entity name="account">
      <filter type="and">
        <condition attribute="statecode" operator="eq" value="0"/>
      </filter>
    </entity>
  </fetch>
  <fetch version="1.0">
    <entity name="bookableresource">
      <filter type="and">
        <condition attribute="statecode" operator="eq" value="0"/>
      </filter>
    </entity>
  </fetch>
  <fetch version="1.0">
    <entity name="bookableresourcecategory">
      <filter type="and">
        <condition attribute="statecode" operator="eq" value="0"/>
      </filter>
    </entity>
  </fetch>
  <fetch version="1.0">
    <entity name="bookableresourcecharacteristic">
      <filter type="and">
        <condition attribute="statecode" operator="eq" value="0"/>
      </filter>
    </entity>
  </fetch>
  <fetch version="1.0">
    <entity name="bookingstatus">
      <filter type="and">
        <condition attribute="statecode" operator="eq" value="0"/>
      </filter>
    </entity>
  </fetch>
  <fetch version="1.0">
    <entity name="campaign">
      <filter type="and">
        <condition attribute="statecode" operator="eq" value="0"/>
      </filter>
    </entity>
  </fetch>
  <fetch version="1.0">
    <entity name="characteristic">
      <filter type="and">
        <condition attribute="statecode" operator="eq" value="0"/>
      </filter>
    </entity>
  </fetch>
  <fetch version="1.0">
    <entity name="connection">
      <filter type="and">
        <condition attribute="connectionid" operator="not-null"/>
      </filter>
    </entity>
  </fetch>
  <fetch version="1.0">
    <entity name="connectionrole">
      <filter type="and">
        <condition attribute="connectionroleid" operator="eq" value="9c86f660-5f5b-e611-810b-00155dbd6a1d" uitype="connectionrole" uiname="Connected IoT Device"/>
      </filter>
    </entity>
  </fetch>
  <fetch version="1.0">
    <entity name="discounttype">
      <filter type="and">
        <condition attribute="statecode" operator="eq" value="0"/>
      </filter>
    </entity>
  </fetch>
  <fetch version="1.0">
    <entity name="businessunit">
      <filter type="and">
        <condition attribute="isdisabled" operator="eq" value="0"/>
      </filter>
    </entity>
  </fetch>
  <fetch version="1.0">
    <entity name="contact">
      <filter type="and">
        <condition attribute="statecode" operator="eq" value="0"/>
      </filter>
    </entity>
  </fetch>
  <fetch version="1.0">
    <entity name="resco_mobilereport">
      <filter type="and">
        <condition attribute="statuscode" operator="eq" value="1"/>
      </filter>
    </entity>
  </fetch>
  <fetch version="1.0">
    <entity name="uomschedule">
      <filter type="and">
        <condition attribute="statecode" operator="eq" value="0"/>
      </filter>
    </entity>
  </fetch>
  <fetch version="1.0">
    <entity name="quote">
      <filter type="and">
        <condition attribute="modifiedon" operator="last-x-days" value="30"/>
        <condition attribute="statecode" operator="ne" value="0"/>
      </filter>
    </entity>
  </fetch>
  <fetch version="1.0">
    <entity name="salesorder">
      <filter type="and">
        <condition attribute="modifiedon" operator="last-x-days" value="30"/>
        <condition attribute="statecode" operator="eq" value="0"/>
      </filter>
    </entity>
  </fetch>
  <fetch version="1.0">
    <entity name="invoice">
      <filter type="and">
        <condition attribute="modifiedon" operator="last-x-days" value="30"/>
        <condition attribute="statecode" operator="eq" value="0"/>
      </filter>
    </entity>
  </fetch>
  <fetch version="1.0">
    <entity name="systemuser">
      <filter type="and">
        <condition attribute="isdisabled" operator="eq" value="0"/>
        <condition attribute="iroc_routebookuser" operator="eq" value="1"/>
      </filter>
    </entity>
  </fetch>
  <fetch version="1.0">
    <entity name="lead">
      <filter type="and">
        <condition attribute="statecode" operator="eq" value="0"/>
      </filter>
    </entity>
  </fetch>
  <fetch version="1.0">
    <entity name="msdyn_bookingsetupmetadata">
      <filter type="and">
        <condition attribute="statecode" operator="eq" value="0"/>
      </filter>
    </entity>
  </fetch>
  <fetch version="1.0">
    <entity name="opportunity">
      <filter type="and">
        <condition attribute="modifiedon" operator="last-x-days" value="60"/>
        <condition attribute="statecode" operator="eq" value="0"/>
      </filter>
    </entity>
  </fetch>
  <fetch version="1.0">
    <entity name="email">
      <filter type="and">
        <condition attribute="modifiedon" operator="last-x-days" value="10"/>
      </filter>
    </entity>
  </fetch>
  <fetch version="1.0">
    <entity name="phonecall">
      <filter type="and">
        <condition attribute="modifiedon" operator="last-x-days" value="10"/>
      </filter>
    </entity>
  </fetch>
  <fetch version="1.0">
    <entity name="task">
      <filter type="and">
        <condition attribute="modifiedon" operator="last-x-days" value="10"/>
        <condition attribute="statecode" operator="eq" value="0"/>
      </filter>
    </entity>
  </fetch>
  <fetch version="1.0">
    <entity name="transactioncurrency">
      <filter type="and">
        <condition attribute="statecode" operator="eq" value="0"/>
      </filter>
    </entity>
  </fetch>
  <fetch version="1.0">
    <entity name="appointment">
      <filter type="and">
        <condition attribute="modifiedon" operator="last-x-days" value="10"/>
        <condition attribute="isdraft" operator="eq" value="0"/>
      </filter>
    </entity>
  </fetch>
  <fetch version="1.0">
    <entity name="incident">
      <filter type="and">
        <condition attribute="modifiedon" operator="last-x-days" value="15"/>
        <condition attribute="statecode" operator="eq" value="0"/>
      </filter>
    </entity>
  </fetch>
  <fetch version="1.0">
    <entity name="msdyn_taxcodedetail">
      <filter type="and">
        <condition attribute="statecode" operator="eq" value="0"/>
      </filter>
    </entity>
  </fetch>
  <fetch version="1.0">
    <entity name="pricelevel">
      <filter type="and">
        <condition attribute="statecode" operator="eq" value="0"/>
      </filter>
    </entity>
  </fetch>
  <fetch version="1.0">
    <entity name="msdyn_customerasset">
      <filter type="and">
        <condition attribute="statecode" operator="eq" value="0"/>
      </filter>
      <link-entity name="account" alias="L6" from="accountid" to="msdyn_account" link-type="inner">
        <filter type="and">
          <condition attribute="statecode" operator="eq" value="0"/>
        </filter>
        <link-entity name="msdyn_workorder" alias="L7" from="msdyn_serviceaccount" to="accountid" link-type="inner">
          <filter type="and">
            <condition attribute="statecode" operator="eq" value="0"/>
            <condition attribute="msdyn_systemstatus" operator="in">
              <value>690970000</value>
              <value>690970001</value>
              <value>690970002</value>
              <value>690970003</value>
            </condition>
          </filter>
          <link-entity name="bookableresourcebooking" alias="L8" from="msdyn_workorder" to="msdyn_workorderid" link-type="inner">
            <filter type="and">
              <condition attribute="statecode" operator="eq" value="0"/>
              <filter type="or">
                <condition attribute="starttime" operator="next-x-days" value="7"/>
                <condition attribute="starttime" operator="today"/>
                <condition attribute="endtime" operator="next-x-days" value="7"/>
                <condition attribute="endtime" operator="today"/>
              </filter>
            </filter>
            <link-entity name="bookingstatus" alias="L9" from="bookingstatusid" to="bookingstatus" link-type="inner">
              <filter type="and">
                <condition attribute="msdyn_fieldservicestatus" operator="in">
                  <value>690970000</value>
                  <value>690970001</value>
                  <value>690970002</value>
                  <value>690970003</value>
                </condition>
                <condition attribute="statecode" operator="eq" value="0"/>
              </filter>
            </link-entity>
            <link-entity name="bookableresource" alias="L10" from="bookableresourceid" to="resource" link-type="inner">
              <filter type="and">
                <condition attribute="userid" operator="eq-userid"/>
                <condition attribute="statecode" operator="eq" value="0"/>
              </filter>
            </link-entity>
          </link-entity>
        </link-entity>
      </link-entity>
    </entity>
  </fetch>
  <fetch version="1.0">
    <entity name="msdyn_fieldservicepricelistitem">
      <filter type="and">
        <condition attribute="statecode" operator="eq" value="0"/>
      </filter>
    </entity>
  </fetch>
  <fetch version="1.0">
    <entity name="msdyn_incidenttype">
      <filter type="and">
        <condition attribute="statecode" operator="eq" value="0"/>
      </filter>
    </entity>
  </fetch>
  <fetch version="1.0">
    <entity name="msdyn_priority">
      <filter type="and">
        <condition attribute="statecode" operator="eq" value="0"/>
      </filter>
    </entity>
  </fetch>
  <fetch version="1.0">
    <entity name="msdyn_productinventory">
      <filter type="and">
        <condition attribute="statecode" operator="eq" value="0"/>
      </filter>
    </entity>
  </fetch>
  <fetch version="1.0">
    <entity name="msdyn_resourcepaytype">
      <filter type="and">
        <condition attribute="statecode" operator="eq" value="0"/>
      </filter>
    </entity>
  </fetch>
  <fetch version="1.0">
    <entity name="msdyn_servicetasktype">
      <filter type="and">
        <condition attribute="statecode" operator="eq" value="0"/>
      </filter>
    </entity>
  </fetch>
  <fetch version="1.0">
    <entity name="msdyn_shipvia">
      <filter type="and">
        <condition attribute="statecode" operator="eq" value="0"/>
      </filter>
    </entity>
  </fetch>
  <fetch version="1.0">
    <entity name="msdyn_taxcode">
      <filter type="and">
        <condition attribute="statecode" operator="eq" value="0"/>
      </filter>
    </entity>
  </fetch>
  <fetch version="1.0">
    <entity name="product">
      <filter type="and">
        <condition attribute="statecode" operator="eq" value="0"/>
      </filter>
    </entity>
  </fetch>
  <fetch version="1.0">
    <entity name="service">
      <filter type="and">
        <condition attribute="isschedulable" operator="eq" value="1"/>
        <condition attribute="isvisible" operator="eq" value="1"/>
      </filter>
    </entity>
  </fetch>
  <fetch version="1.0">
    <entity name="msdyn_workorder">
      <filter type="and">
        <condition attribute="statecode" operator="in">
          <value>0</value>
          <value>1</value>
        </condition>
        <filter type="or">
          <condition attribute="createdon" operator="last-x-days" value="7"/>
          <condition attribute="createdon" operator="next-x-months" value="3"/>
          <condition attribute="createdon" operator="this-month"/>
        </filter>
      </filter>
    </entity>
  </fetch>
  <fetch version="1.0">
    <entity name="bookableresourcebooking">
      <filter type="and">
        <filter type="or">
          <condition attribute="starttime" operator="this-month"/>
          <condition attribute="starttime" operator="last-x-days" value="7"/>
          <condition attribute="starttime" operator="next-x-months" value="3"/>
        </filter>
      </filter>
    </entity>
  </fetch>
  <fetch version="1.0">
    <entity name="msdyn_workorderproduct">
      <filter type="and">
        <condition attribute="statecode" operator="eq" value="0"/>
      </filter>
      <link-entity name="msdyn_workorder" alias="L0" from="msdyn_workorderid" to="msdyn_workorder" link-type="inner">
        <filter type="and">
          <condition attribute="statecode" operator="eq" value="0"/>
          <condition attribute="msdyn_systemstatus" operator="in">
            <value>690970003</value>
            <value>690970002</value>
            <value>690970001</value>
            <value>690970000</value>
          </condition>
        </filter>
        <link-entity name="bookableresourcebooking" alias="L1" from="msdyn_workorder" to="msdyn_workorderid" link-type="inner">
          <filter type="and">
            <condition attribute="statecode" operator="eq" value="0"/>
            <filter type="or">
              <condition attribute="starttime" operator="next-x-days" value="7"/>
              <condition attribute="starttime" operator="today"/>
              <condition attribute="endtime" operator="next-x-days" value="7"/>
              <condition attribute="endtime" operator="today"/>
            </filter>
          </filter>
          <link-entity name="bookingstatus" alias="L2" from="bookingstatusid" to="bookingstatus" link-type="inner">
            <filter type="and">
              <condition attribute="statecode" operator="eq" value="0"/>
              <condition attribute="msdyn_fieldservicestatus" operator="in">
                <value>690970003</value>
                <value>690970002</value>
                <value>690970001</value>
                <value>690970000</value>
              </condition>
            </filter>
          </link-entity>
          <link-entity name="bookableresource" alias="L3" from="bookableresourceid" to="resource" link-type="inner">
            <filter type="and">
              <condition attribute="userid" operator="eq-userid"/>
              <condition attribute="statecode" operator="eq" value="0"/>
            </filter>
          </link-entity>
        </link-entity>
      </link-entity>
    </entity>
  </fetch>
  <fetch version="1.0">
    <entity name="msdyn_workorderincident">
      <filter type="and">
        <condition attribute="statecode" operator="eq" value="0"/>
      </filter>
      <link-entity name="msdyn_workorder" alias="L0" from="msdyn_workorderid" to="msdyn_workorder" link-type="inner">
        <filter type="and">
          <condition attribute="statecode" operator="eq" value="0"/>
          <condition attribute="msdyn_systemstatus" operator="in">
            <value>690970003</value>
            <value>690970002</value>
            <value>690970001</value>
            <value>690970000</value>
          </condition>
        </filter>
        <link-entity name="bookableresourcebooking" alias="L1" from="msdyn_workorder" to="msdyn_workorderid" link-type="inner">
          <filter type="and">
            <condition attribute="statecode" operator="eq" value="0"/>
            <filter type="or">
              <condition attribute="starttime" operator="next-x-days" value="7"/>
              <condition attribute="starttime" operator="today"/>
              <condition attribute="endtime" operator="next-x-days" value="7"/>
              <condition attribute="endtime" operator="today"/>
            </filter>
          </filter>
          <link-entity name="bookingstatus" alias="L2" from="bookingstatusid" to="bookingstatus" link-type="inner">
            <filter type="and">
              <condition attribute="statecode" operator="eq" value="0"/>
              <condition attribute="msdyn_fieldservicestatus" operator="in">
                <value>690970003</value>
                <value>690970002</value>
                <value>690970001</value>
                <value>690970000</value>
              </condition>
            </filter>
          </link-entity>
          <link-entity name="bookableresource" alias="L3" from="bookableresourceid" to="resource" link-type="inner">
            <filter type="and">
              <condition attribute="userid" operator="eq-userid"/>
              <condition attribute="statecode" operator="eq" value="0"/>
            </filter>
          </link-entity>
        </link-entity>
      </link-entity>
    </entity>
  </fetch>
  <fetch version="1.0">
    <entity name="msdyn_workorderservice">
      <filter type="and">
        <condition attribute="statecode" operator="eq" value="0"/>
      </filter>
      <link-entity name="msdyn_workorder" alias="L0" from="msdyn_workorderid" to="msdyn_workorder" link-type="inner">
        <filter type="and">
          <condition attribute="statecode" operator="eq" value="0"/>
          <condition attribute="msdyn_systemstatus" operator="in">
            <value>690970003</value>
            <value>690970002</value>
            <value>690970001</value>
            <value>690970000</value>
          </condition>
        </filter>
        <link-entity name="bookableresourcebooking" alias="L1" from="msdyn_workorder" to="msdyn_workorderid" link-type="inner">
          <filter type="and">
            <condition attribute="statecode" operator="eq" value="0"/>
            <filter type="or">
              <condition attribute="starttime" operator="next-x-days" value="7"/>
              <condition attribute="starttime" operator="today"/>
              <condition attribute="endtime" operator="next-x-days" value="7"/>
              <condition attribute="endtime" operator="today"/>
            </filter>
          </filter>
          <link-entity name="bookingstatus" alias="L2" from="bookingstatusid" to="bookingstatus" link-type="inner">
            <filter type="and">
              <condition attribute="statecode" operator="eq" value="0"/>
              <condition attribute="msdyn_fieldservicestatus" operator="in">
                <value>690970003</value>
                <value>690970002</value>
                <value>690970001</value>
                <value>690970000</value>
              </condition>
            </filter>
          </link-entity>
          <link-entity name="bookableresource" alias="L3" from="bookableresourceid" to="resource" link-type="inner">
            <filter type="and">
              <condition attribute="userid" operator="eq-userid"/>
              <condition attribute="statecode" operator="eq" value="0"/>
            </filter>
          </link-entity>
        </link-entity>
      </link-entity>
    </entity>
  </fetch>
  <fetch version="1.0">
    <entity name="msdyn_workorderservicetask">
      <filter type="and">
        <condition attribute="statecode" operator="eq" value="0"/>
      </filter>
      <link-entity name="msdyn_workorder" alias="L0" from="msdyn_workorderid" to="msdyn_workorder" link-type="inner">
        <filter type="and">
          <condition attribute="statecode" operator="eq" value="0"/>
          <condition attribute="msdyn_systemstatus" operator="in">
            <value>690970003</value>
            <value>690970002</value>
            <value>690970001</value>
            <value>690970000</value>
          </condition>
        </filter>
        <link-entity name="bookableresourcebooking" alias="L1" from="msdyn_workorder" to="msdyn_workorderid" link-type="inner">
          <filter type="and">
            <condition attribute="statecode" operator="eq" value="0"/>
            <filter type="or">
              <condition attribute="starttime" operator="next-x-days" value="7"/>
              <condition attribute="starttime" operator="today"/>
              <condition attribute="endtime" operator="next-x-days" value="7"/>
              <condition attribute="endtime" operator="today"/>
            </filter>
          </filter>
          <link-entity name="bookingstatus" alias="L2" from="bookingstatusid" to="bookingstatus" link-type="inner">
            <filter type="and">
              <condition attribute="statecode" operator="eq" value="0"/>
              <condition attribute="msdyn_fieldservicestatus" operator="in">
                <value>690970003</value>
                <value>690970002</value>
                <value>690970001</value>
                <value>690970000</value>
              </condition>
            </filter>
          </link-entity>
          <link-entity name="bookableresource" alias="L3" from="bookableresourceid" to="resource" link-type="inner">
            <filter type="and">
              <condition attribute="userid" operator="eq-userid"/>
              <condition attribute="statecode" operator="eq" value="0"/>
            </filter>
          </link-entity>
        </link-entity>
      </link-entity>
    </entity>
  </fetch>
  <fetch version="1.0">
    <entity name="msdyn_bookingtimestamp">
      <filter type="and">
        <condition attribute="createdon" operator="lt" value="1850-11-15"/>
      </filter>
    </entity>
  </fetch>
  <fetch version="1.0">
    <entity name="msdyn_agreement">
      <filter type="and">
        <condition attribute="statecode" operator="eq" value="0"/>
        <condition attribute="msdyn_systemstatus" operator="in">
          <value>690970001</value>
          <value>690970000</value>
        </condition>
        <condition attribute="modifiedon" operator="last-x-days" value="10"/>
      </filter>
    </entity>
  </fetch>
  <fetch version="1.0">
    <entity name="msdyn_agreementbookingincident">
      <filter type="and">
        <condition attribute="statecode" operator="eq" value="0"/>
        <condition attribute="msdyn_name" operator="eq" value="@NameFilter@"/>
      </filter>
    </entity>
  </fetch>
  <fetch version="1.0">
    <entity name="msdyn_agreementinvoicedate">
      <filter type="and">
        <condition attribute="statecode" operator="eq" value="0"/>
        <condition attribute="msdyn_name" operator="eq" value="@NameFilter@"/>
      </filter>
    </entity>
  </fetch>
  <fetch version="1.0">
    <entity name="msdyn_agreementinvoiceproduct">
      <filter type="and">
        <condition attribute="statecode" operator="eq" value="0"/>
        <condition attribute="msdyn_name" operator="eq" value="@NameFilter@"/>
      </filter>
    </entity>
  </fetch>
  <fetch version="1.0">
    <entity name="msdyn_agreementinvoicesetup">
      <filter type="and">
        <condition attribute="statecode" operator="eq" value="0"/>
        <condition attribute="msdyn_name" operator="eq" value="@NameFilter@"/>
      </filter>
    </entity>
  </fetch>
  <fetch version="1.0">
    <entity name="msdyn_agreementbookingproduct">
      <filter type="and">
        <condition attribute="statecode" operator="eq" value="0"/>
        <condition attribute="msdyn_name" operator="eq" value="@NameFilter@"/>
      </filter>
    </entity>
  </fetch>
  <fetch version="1.0">
    <entity name="msdyn_agreementbookingsetup">
      <filter type="and">
        <condition attribute="statecode" operator="eq" value="0"/>
        <condition attribute="msdyn_name" operator="eq" value="@NameFilter@"/>
      </filter>
    </entity>
  </fetch>
  <fetch version="1.0">
    <entity name="msdyn_agreementbookingdate">
      <filter type="and">
        <condition attribute="statecode" operator="eq" value="0"/>
        <condition attribute="msdyn_name" operator="eq" value="@NameFilter@"/>
      </filter>
    </entity>
  </fetch>
  <fetch version="1.0">
    <entity name="msdyn_agreementbookingservice">
      <filter type="and">
        <condition attribute="statecode" operator="eq" value="0"/>
        <condition attribute="msdyn_name" operator="eq" value="@NameFilter@"/>
      </filter>
    </entity>
  </fetch>
  <fetch version="1.0">
    <entity name="msdyn_agreementbookingservicetask">
      <filter type="and">
        <condition attribute="statecode" operator="eq" value="0"/>
        <condition attribute="msdyn_name" operator="eq" value="@NameFilter@"/>
      </filter>
    </entity>
  </fetch>
  <fetch version="1.0">
    <entity name="msdyn_iotalert">
      <link-entity name="msdyn_iotdevice" alias="L0" from="msdyn_iotdeviceid" to="msdyn_device" link-type="inner">
        <link-entity name="account" alias="L6" from="accountid" to="msdyn_account" link-type="inner">
          <filter type="and">
            <condition attribute="statecode" operator="eq" value="0"/>
          </filter>
          <link-entity name="msdyn_workorder" alias="L7" from="msdyn_serviceaccount" to="accountid" link-type="inner">
            <filter type="and">
              <condition attribute="statecode" operator="eq" value="0"/>
              <condition attribute="msdyn_systemstatus" operator="in">
                <value>690970000</value>
                <value>690970001</value>
                <value>690970002</value>
                <value>690970003</value>
              </condition>
            </filter>
            <link-entity name="bookableresourcebooking" alias="L8" from="msdyn_workorder" to="msdyn_workorderid" link-type="inner">
              <filter type="and">
                <condition attribute="statecode" operator="eq" value="0"/>
                <filter type="or">
                  <condition attribute="starttime" operator="next-x-days" value="7"/>
                  <condition attribute="starttime" operator="today"/>
                  <condition attribute="endtime" operator="next-x-days" value="7"/>
                  <condition attribute="endtime" operator="today"/>
                </filter>
              </filter>
              <link-entity name="bookingstatus" alias="L9" from="bookingstatusid" to="bookingstatus" link-type="inner">
                <filter type="and">
                  <condition attribute="msdyn_fieldservicestatus" operator="in">
                    <value>690970000</value>
                    <value>690970001</value>
                    <value>690970002</value>
                    <value>690970003</value>
                  </condition>
                  <condition attribute="statecode" operator="eq" value="0"/>
                </filter>
              </link-entity>
              <link-entity name="bookableresource" alias="L10" from="bookableresourceid" to="resource" link-type="inner">
                <filter type="and">
                  <condition attribute="userid" operator="eq-userid"/>
                  <condition attribute="statecode" operator="eq" value="0"/>
                </filter>
              </link-entity>
            </link-entity>
          </link-entity>
        </link-entity>
      </link-entity>
    </entity>
  </fetch>
  <fetch version="1.0">
    <entity name="msdyn_iotdevice">
      <link-entity name="account" alias="L6" from="accountid" to="msdyn_account" link-type="inner">
        <filter type="and">
          <condition attribute="statecode" operator="eq" value="0"/>
        </filter>
        <link-entity name="msdyn_workorder" alias="L7" from="msdyn_serviceaccount" to="accountid" link-type="inner">
          <filter type="and">
            <condition attribute="statecode" operator="eq" value="0"/>
            <condition attribute="msdyn_systemstatus" operator="in">
              <value>690970000</value>
              <value>690970001</value>
              <value>690970002</value>
              <value>690970003</value>
            </condition>
          </filter>
          <link-entity name="bookableresourcebooking" alias="L8" from="msdyn_workorder" to="msdyn_workorderid" link-type="inner">
            <filter type="and">
              <condition attribute="statecode" operator="eq" value="0"/>
              <filter type="or">
                <condition attribute="starttime" operator="next-x-days" value="7"/>
                <condition attribute="starttime" operator="today"/>
                <condition attribute="endtime" operator="next-x-days" value="7"/>
                <condition attribute="endtime" operator="today"/>
              </filter>
            </filter>
            <link-entity name="bookingstatus" alias="L9" from="bookingstatusid" to="bookingstatus" link-type="inner">
              <filter type="and">
                <condition attribute="msdyn_fieldservicestatus" operator="in">
                  <value>690970000</value>
                  <value>690970001</value>
                  <value>690970002</value>
                  <value>690970003</value>
                </condition>
                <condition attribute="statecode" operator="eq" value="0"/>
              </filter>
            </link-entity>
            <link-entity name="bookableresource" alias="L10" from="bookableresourceid" to="resource" link-type="inner">
              <filter type="and">
                <condition attribute="userid" operator="eq-userid"/>
                <condition attribute="statecode" operator="eq" value="0"/>
              </filter>
            </link-entity>
          </link-entity>
        </link-entity>
      </link-entity>
    </entity>
  </fetch>
  <fetch version="1.0">
    <entity name="msdyn_iotdevicecommand">
      <link-entity name="msdyn_iotdevice" alias="L0" from="msdyn_iotdeviceid" to="msdyn_device" link-type="inner">
        <link-entity name="account" alias="L6" from="accountid" to="msdyn_account" link-type="inner">
          <filter type="and">
            <condition attribute="statecode" operator="eq" value="0"/>
          </filter>
          <link-entity name="msdyn_workorder" alias="L7" from="msdyn_serviceaccount" to="accountid" link-type="inner">
            <filter type="and">
              <condition attribute="statecode" operator="eq" value="0"/>
              <condition attribute="msdyn_systemstatus" operator="in">
                <value>690970000</value>
                <value>690970001</value>
                <value>690970002</value>
                <value>690970003</value>
              </condition>
            </filter>
            <link-entity name="bookableresourcebooking" alias="L8" from="msdyn_workorder" to="msdyn_workorderid" link-type="inner">
              <filter type="and">
                <condition attribute="statecode" operator="eq" value="0"/>
                <filter type="or">
                  <condition attribute="starttime" operator="next-x-days" value="7"/>
                  <condition attribute="starttime" operator="today"/>
                  <condition attribute="endtime" operator="next-x-days" value="7"/>
                  <condition attribute="endtime" operator="today"/>
                </filter>
              </filter>
              <link-entity name="bookingstatus" alias="L9" from="bookingstatusid" to="bookingstatus" link-type="inner">
                <filter type="and">
                  <condition attribute="msdyn_fieldservicestatus" operator="in">
                    <value>690970000</value>
                    <value>690970001</value>
                    <value>690970002</value>
                    <value>690970003</value>
                  </condition>
                  <condition attribute="statecode" operator="eq" value="0"/>
                </filter>
              </link-entity>
              <link-entity name="bookableresource" alias="L10" from="bookableresourceid" to="resource" link-type="inner">
                <filter type="and">
                  <condition attribute="userid" operator="eq-userid"/>
                  <condition attribute="statecode" operator="eq" value="0"/>
                </filter>
              </link-entity>
            </link-entity>
          </link-entity>
        </link-entity>
      </link-entity>
    </entity>
  </fetch>
  <fetch version="1.0">
    <entity name="msdyn_rma">
      <filter type="and">
        <condition attribute="statecode" operator="eq" value="0"/>
      </filter>
    </entity>
  </fetch>
  <fetch version="1.0">
    <entity name="msdyn_rmaproduct">
      <filter type="and">
        <condition attribute="statecode" operator="eq" value="0"/>
      </filter>
    </entity>
  </fetch>
  <fetch version="1.0">
    <entity name="msdyn_rmareceipt">
      <filter type="and">
        <condition attribute="statecode" operator="eq" value="0"/>
      </filter>
    </entity>
  </fetch>
  <fetch version="1.0">
    <entity name="msdyn_rmareceiptproduct">
      <filter type="and">
        <condition attribute="statecode" operator="eq" value="0"/>
      </filter>
    </entity>
  </fetch>
  <fetch version="1.0">
    <entity name="msdyn_rtv">
      <filter type="and">
        <condition attribute="statecode" operator="eq" value="0"/>
      </filter>
    </entity>
  </fetch>
  <fetch version="1.0">
    <entity name="msdyn_rtvproduct">
      <filter type="and">
        <condition attribute="statecode" operator="eq" value="0"/>
      </filter>
    </entity>
  </fetch>
  <fetch version="1.0">
    <entity name="msdyn_timeoffrequest">
      <filter type="and">
        <condition attribute="statecode" operator="eq" value="0"/>
      </filter>
    </entity>
  </fetch>
  <fetch version="1.0">
    <entity name="msdyn_warehouse">
      <filter type="and">
        <condition attribute="statecode" operator="eq" value="0"/>
      </filter>
    </entity>
  </fetch>
  <fetch version="1.0">
    <entity name="msdyn_workordersubstatus">
      <filter type="and">
        <condition attribute="statecode" operator="eq" value="0"/>
      </filter>
    </entity>
  </fetch>
  <fetch version="1.0">
    <entity name="msdyn_workordertype">
      <filter type="and">
        <condition attribute="statecode" operator="eq" value="0"/>
      </filter>
    </entity>
  </fetch>
  <fetch version="1.0">
    <entity name="workflow">
      <filter type="and">
        <condition attribute="statuscode" operator="eq" value="2"/>
        <condition attribute="category" operator="eq" value="4"/>
      </filter>
    </entity>
  </fetch>
  <fetch version="1.0">
    <entity name="iroc_routefeed">
      <filter type="and">
        <condition attribute="createdon" operator="last-x-months" value="3"/>
      </filter>
    </entity>
  </fetch>
  <fetch version="1.0">
    <entity name="iroc_tier">
      <filter type="and">
        <condition attribute="statecode" operator="eq" value="0"/>
      </filter>
    </entity>
  </fetch>
  <fetch version="1.0">
    <entity name="iroc_notificationsend">
      <filter type="and">
        <condition attribute="createdon" operator="last-x-days" value="120"/>
        <condition attribute="iroc_notificationtype" operator="eq" value="929530000"/>
      </filter>
    </entity>
  </fetch>
  <fetch version="1.0">
    <entity name="iroc_leaseinspection">
      <filter type="and">
        <filter type="or">
          <condition attribute="createdon" operator="last-x-weeks" value="24"/>
          <condition attribute="createdon" operator="this-week"/>
        </filter>
      </filter>
    </entity>
  </fetch>
  <fetch version="1.0">
    <entity name="msdyn_resourcerequirement">
      <filter type="and">
        <filter type="or">
          <condition attribute="createdon" operator="last-x-months" value="3"/>
          <condition attribute="createdon" operator="next-month"/>
          <condition attribute="createdon" operator="next-x-months" value="4"/>
        </filter>
      </filter>
    </entity>
  </fetch>
  <fetch version="1.0">
    <entity name="iroc_jobtransaction">
      <filter type="and">
        <condition attribute="createdon" operator="not-null"/>
      </filter>
    </entity>
  </fetch>
  <fetch version="1.0">
    <entity name="postregarding">
      <filter type="and">
        <condition attribute="latestmanualpostmodifiedon" operator="not-null"/>
      </filter>
    </entity>
  </fetch>
</fetchcollection>